odoo/addons/sale_coupon_validity_notification/README.rst
odoo/addons/sale_coupon_validity_notification/__init__.py
odoo/addons/sale_coupon_validity_notification/__manifest__.py
odoo/addons/sale_coupon_validity_notification/i18n/es.po
odoo/addons/sale_coupon_validity_notification/i18n/sale_coupon_validity_notification.pot
odoo/addons/sale_coupon_validity_notification/models/__init__.py
odoo/addons/sale_coupon_validity_notification/models/coupon.py
odoo/addons/sale_coupon_validity_notification/readme/CONTRIBUTORS.rst
odoo/addons/sale_coupon_validity_notification/readme/DESCRIPTION.rst
odoo/addons/sale_coupon_validity_notification/readme/USAGE.rst
odoo/addons/sale_coupon_validity_notification/static/description/icon.png
odoo/addons/sale_coupon_validity_notification/static/description/index.html
odoo/addons/sale_coupon_validity_notification/tests/__init__.py
odoo/addons/sale_coupon_validity_notification/tests/test_sale_coupon_validity_notification.py
odoo_addon_sale_coupon_validity_notification-15.0.1.0.0.4.dist-info/METADATA
odoo_addon_sale_coupon_validity_notification-15.0.1.0.0.4.dist-info/WHEEL
odoo_addon_sale_coupon_validity_notification-15.0.1.0.0.4.dist-info/top_level.txt
odoo_addon_sale_coupon_validity_notification-15.0.1.0.0.4.dist-info/RECORD
